ibm_db_dbi
config
ibm_db
testfunctions
tests
