Metadata-Version: 1.1
Name: ibm-db-py3
Version: 2.0.4.2
Summary: Python DBI driver for DB2 (LUW, zOS, i5) and IDS
Home-page: http://pypi.python.org/pypi/ibm_db/
Author: IBM Application Development Team
Author-email: opendev@us.ibm.com
License: Apache License 2.0
Download-URL: http://code.google.com/p/ibm-db/downloads/list
Keywords: database DB-API interface IBM Data Servers DB2 Informix IDS
Platform: LinuxIA32
Platform: Win32
Classifier: Development Status :: 4 - Beta
Classifier: Intended Audience :: Developers
Classifier: License :: OSI Approved :: Apache Software License
Classifier: Operating System :: Unix
Classifier: Topic :: Database :: Front-Ends
